technical_analysis/__init__.py
technical_analysis/_common.py
technical_analysis/hurst.py
technical_analysis/indicators.py
technical_analysis/moving_average.py
technical_analysis/overlays.py
technical_analysis/stats.py
technical_analysis/utils.py
technical_analysis/backtest/__init__.py
technical_analysis/backtest/backtest.py
technical_analysis/backtest/strategy.py
technical_analysis/candles/__init__.py
technical_analysis/candles/continuation.py
technical_analysis/candles/reversal.py
technical_analysis/candles/single.py
technical_analysis/data/__init__.py
technical_analysis/data/generate.py
technical_analysis-0.0.6.dist-info/LICENSE
technical_analysis-0.0.6.dist-info/METADATA
technical_analysis-0.0.6.dist-info/WHEEL
technical_analysis-0.0.6.dist-info/top_level.txt
technical_analysis-0.0.6.dist-info/RECORD
