Metadata-Version: 2.1
Name: technical_analysis
Version: 0.0.6
Summary: Technical Analysis with Python
Home-page: https://github.com/trevormcguire/technical-analysis
Author: Trevor McGuire
Author-email: trevormcguire13@gmail.com
Maintainer: Trevor McGuire
License: BSD 3-Clause License
Classifier: Programming Language :: Python :: 3
Classifier: Programming Language :: Python :: Implementation :: CPython
Classifier: Development Status :: 4 - Beta
License-File: LICENSE
Requires-Dist: numpy
Requires-Dist: pandas
